eff_tao_encryption/__init__.py
eff_tao_encryption/backend.cpython-312-x86_64-linux-gnu.so
eff_tao_encryption/package_info.py
eff_tao_encryption/tao_codec/__init__.py
eff_tao_encryption/tao_codec/tao_codec.py
nvidia_eff_tao_encryption.libs/libcom_err-2abe824b.so.2.1
nvidia_eff_tao_encryption.libs/libcrypto-d3570994.so.1.0.2k
nvidia_eff_tao_encryption.libs/libgssapi_krb5-497db0c6.so.2.2
nvidia_eff_tao_encryption.libs/libk5crypto-b1f99d5c.so.3.1
nvidia_eff_tao_encryption.libs/libkeyutils-dfe70bd6.so.1.5
nvidia_eff_tao_encryption.libs/libkrb5-fcafa220.so.3.3
nvidia_eff_tao_encryption.libs/libkrb5support-d0bcff84.so.0.1
nvidia_eff_tao_encryption.libs/libpcre-9513aab5.so.1.2.0
nvidia_eff_tao_encryption.libs/libselinux-0922c95c.so.1
nvidia_eff_tao_encryption.libs/libssl-cd1d6220.so.1.0.2k
pyarmor_runtime_001219/__init__.py
pyarmor_runtime_001219/pyarmor_runtime.so
nvidia_eff_tao_encryption-0.1.10.dist-info/METADATA
nvidia_eff_tao_encryption-0.1.10.dist-info/WHEEL
nvidia_eff_tao_encryption-0.1.10.dist-info/top_level.txt
nvidia_eff_tao_encryption-0.1.10.dist-info/RECORD
nvidia_eff_tao_encryption-0.1.10.dist-info/licenses/LICENSE.txt
